dis_client_sdk/DisClient.py
dis_client_sdk/README.md
dis_client_sdk/__init__.py
dis_client_sdk-0.0.2.dist-info/DESCRIPTION.rst
dis_client_sdk-0.0.2.dist-info/METADATA
dis_client_sdk-0.0.2.dist-info/RECORD
dis_client_sdk-0.0.2.dist-info/WHEEL
dis_client_sdk-0.0.2.dist-info/metadata.json
dis_client_sdk-0.0.2.dist-info/top_level.txt
