Metadata-Version: 2.0
Name: dis-client-sdk
Version: 0.0.2
Summary: DIS Client SDK
Home-page: https://github.com/bjyurkovich
Author: bjyurkovich
Author-email: bj.yurkovich@technicity.io
License: MIT
Platform: UNKNOWN
Classifier: Programming Language :: Python :: 3
Classifier: License :: OSI Approved :: MIT License
Classifier: Operating System :: OS Independent
Requires-Dist: requests
Requires-Dist: pydantic
